{
  "frames": [
    {
      "filename": "nose0000",
      "d": 0.1,
      "frame": {
        "x": 2,
        "y": 2,
        "w": 351,
        "h": 140
      }
    },
    {
      "filename": "nose0001",
      "d": 0.1,
      "frame": {
        "x": 2,
        "y": 2,
        "w": 351,
        "h": 140
      }
    },
    {
      "filename": "nose0002",
      "d": 0.1,
      "frame": {
        "x": 2,
        "y": 2,
        "w": 351,
        "h": 140
      }
    },
    {
      "filename": "nose0003",
      "d": 0.1,
      "frame": {
        "x": 2,
        "y": 2,
        "w": 351,
        "h": 140
      }
    },
    {
      "filename": "nose0004",
      "d": 0.1,
      "frame": {
        "x": 2,
        "y": 2,
        "w": 351,
        "h": 140
      }
    },
    {
      "filename": "nose0005",
      "d": 0.1,
      "frame": {
        "x": 2,
        "y": 2,
        "w": 351,
        "h": 140
      }
    },
    {
      "filename": "nose0006",
      "d": 0.1,
      "frame": {
        "x": 2,
        "y": 2,
        "w": 351,
        "h": 140
      }
    },
    {
      "filename": "nose0007",
      "d": 0.1,
      "frame": {
        "x": 2,
        "y": 2,
        "w": 351,
        "h": 140
      }
    },
    {
      "filename": "nose0008",
      "d": 0.1,
      "frame": {
        "x": 2,
        "y": 2,
        "w": 351,
        "h": 140
      }
    },
    {
      "filename": "nose0009",
      "d": 0.1,
      "frame": {
        "x": 356,
        "y": 2,
        "w": 351,
        "h": 140
      }
    },
    {
      "filename": "nose0010",
      "d": 0.1,
      "frame": {
        "x": 710,
        "y": 2,
        "w": 351,
        "h": 140
      }
    },
    {
      "filename": "nose0011",
      "d": 0.1,
      "frame": {
        "x": 1064,
        "y": 2,
        "w": 351,
        "h": 140
      }
    },
    {
      "filename": "nose0012",
      "d": 0.1,
      "frame": {
        "x": 1418,
        "y": 2,
        "w": 351,
        "h": 140
      }
    },
    {
      "filename": "nose0013",
      "d": 0.1,
      "frame": {
        "x": 2,
        "y": 145,
        "w": 351,
        "h": 140
      }
    },
    {
      "filename": "nose0014",
      "d": 0.1,
      "frame": {
        "x": 356,
        "y": 145,
        "w": 351,
        "h": 140
      }
    },
    {
      "filename": "nose0015",
      "d": 0.1,
      "frame": {
        "x": 710,
        "y": 145,
        "w": 351,
        "h": 140
      }
    },
    {
      "filename": "nose0016",
      "d": 0.1,
      "frame": {
        "x": 1064,
        "y": 145,
        "w": 351,
        "h": 140
      }
    },
    {
      "filename": "nose0017",
      "d": 0.1,
      "frame": {
        "x": 1418,
        "y": 145,
        "w": 351,
        "h": 140
      }
    },
    {
      "filename": "nose0018",
      "d": 0.1,
      "frame": {
        "x": 2,
        "y": 288,
        "w": 351,
        "h": 140
      }
    },
    {
      "filename": "nose0019",
      "d": 0.1,
      "frame": {
        "x": 356,
        "y": 288,
        "w": 351,
        "h": 140
      }
    },
    {
      "filename": "nose0020",
      "d": 0.1,
      "frame": {
        "x": 710,
        "y": 288,
        "w": 351,
        "h": 140
      }
    },
    {
      "filename": "nose0021",
      "d": 0.1,
      "frame": {
        "x": 1064,
        "y": 288,
        "w": 351,
        "h": 140
      }
    },
    {
      "filename": "nose0022",
      "d": 0.1,
      "frame": {
        "x": 1418,
        "y": 288,
        "w": 351,
        "h": 140
      }
    },
    {
      "filename": "nose0023",
      "d": 0.1,
      "frame": {
        "x": 2,
        "y": 431,
        "w": 351,
        "h": 140
      }
    },
    {
      "filename": "nose0024",
      "d": 0.1,
      "frame": {
        "x": 356,
        "y": 431,
        "w": 351,
        "h": 140
      }
    },
    {
      "filename": "nose0025",
      "d": 0.1,
      "frame": {
        "x": 710,
        "y": 431,
        "w": 351,
        "h": 140
      }
    },
    {
      "filename": "nose0026",
      "d": 0.1,
      "frame": {
        "x": 1064,
        "y": 431,
        "w": 351,
        "h": 140
      }
    },
    {
      "filename": "nose0027",
      "d": 0.1,
      "frame": {
        "x": 1418,
        "y": 431,
        "w": 351,
        "h": 140
      }
    },
    {
      "filename": "nose0028",
      "d": 0.1,
      "frame": {
        "x": 2,
        "y": 574,
        "w": 351,
        "h": 140
      }
    },
    {
      "filename": "nose0029",
      "d": 0.1,
      "frame": {
        "x": 356,
        "y": 574,
        "w": 351,
        "h": 140
      }
    },
    {
      "filename": "nose0030",
      "d": 0.1,
      "frame": {
        "x": 710,
        "y": 574,
        "w": 351,
        "h": 140
      }
    },
    {
      "filename": "nose0031",
      "d": 0.1,
      "frame": {
        "x": 1064,
        "y": 574,
        "w": 351,
        "h": 140
      }
    },
    {
      "filename": "nose0032",
      "d": 0.1,
      "frame": {
        "x": 1418,
        "y": 574,
        "w": 351,
        "h": 140
      }
    },
    {
      "filename": "nose0033",
      "d": 0.1,
      "frame": {
        "x": 2,
        "y": 717,
        "w": 351,
        "h": 140
      }
    },
    {
      "filename": "nose0034",
      "d": 0.1,
      "frame": {
        "x": 356,
        "y": 717,
        "w": 351,
        "h": 140
      }
    },
    {
      "filename": "nose0035",
      "d": 0.1,
      "frame": {
        "x": 710,
        "y": 717,
        "w": 351,
        "h": 140
      }
    },
    {
      "filename": "nose0036",
      "d": 0.1,
      "frame": {
        "x": 1064,
        "y": 717,
        "w": 351,
        "h": 140
      }
    },
    {
      "filename": "nose0037",
      "d": 0.1,
      "frame": {
        "x": 1418,
        "y": 717,
        "w": 351,
        "h": 140
      }
    },
    {
      "filename": "nose0038",
      "d": 0.1,
      "frame": {
        "x": 2,
        "y": 860,
        "w": 351,
        "h": 140
      }
    },
    {
      "filename": "nose0039",
      "d": 0.1,
      "frame": {
        "x": 356,
        "y": 860,
        "w": 351,
        "h": 140
      }
    },
    {
      "filename": "nose0040",
      "d": 0.1,
      "frame": {
        "x": 710,
        "y": 860,
        "w": 351,
        "h": 140
      }
    },
    {
      "filename": "nose0041",
      "d": 0.1,
      "frame": {
        "x": 1064,
        "y": 860,
        "w": 351,
        "h": 140
      }
    },
    {
      "filename": "nose0042",
      "d": 0.1,
      "frame": {
        "x": 1418,
        "y": 860,
        "w": 351,
        "h": 140
      }
    },
    {
      "filename": "nose0043",
      "d": 0.1,
      "frame": {
        "x": 2,
        "y": 1003,
        "w": 351,
        "h": 140
      }
    },
    {
      "filename": "nose0044",
      "d": 0.1,
      "frame": {
        "x": 356,
        "y": 1003,
        "w": 351,
        "h": 140
      }
    },
    {
      "filename": "nose0045",
      "d": 0.1,
      "frame": {
        "x": 710,
        "y": 1003,
        "w": 351,
        "h": 140
      }
    },
    {
      "filename": "nose0046",
      "d": 0.1,
      "frame": {
        "x": 1064,
        "y": 1003,
        "w": 351,
        "h": 140
      }
    },
    {
      "filename": "nose0047",
      "d": 0.1,
      "frame": {
        "x": 1418,
        "y": 1003,
        "w": 351,
        "h": 140
      }
    },
    {
      "filename": "nose0048",
      "d": 0.1,
      "frame": {
        "x": 2,
        "y": 1146,
        "w": 351,
        "h": 140
      }
    },
    {
      "filename": "nose0049",
      "d": 0.1,
      "frame": {
        "x": 2,
        "y": 2,
        "w": 351,
        "h": 140
      }
    },
    {
      "filename": "nose0050",
      "d": 0.1,
      "frame": {
        "x": 2,
        "y": 2,
        "w": 351,
        "h": 140
      }
    },
    {
      "filename": "nose0051",
      "d": 0.1,
      "frame": {
        "x": 2,
        "y": 2,
        "w": 351,
        "h": 140
      }
    },
    {
      "filename": "nose0052",
      "d": 0.1,
      "frame": {
        "x": 2,
        "y": 2,
        "w": 351,
        "h": 140
      }
    },
    {
      "filename": "nose0053",
      "d": 0.1,
      "frame": {
        "x": 2,
        "y": 2,
        "w": 351,
        "h": 140
      }
    }
  ],
  "meta": {
    "image": "xhm5313nose.png",
    "size": {
      "w": 1800,
      "h": 1300
    }
  }
}